soundboard_relay/__main__.py
soundboard_relay-0.1.1.dist-info/LICENSE
soundboard_relay-0.1.1.dist-info/METADATA
soundboard_relay-0.1.1.dist-info/WHEEL
soundboard_relay-0.1.1.dist-info/entry_points.txt
soundboard_relay-0.1.1.dist-info/top_level.txt
soundboard_relay-0.1.1.dist-info/RECORD
