Metadata-Version: 2.1
Name: soundboard-relay
Version: 0.1.1
Summary: UNKNOWN
Home-page: UNKNOWN
Author: UNKNOWN
Author-email: UNKNOWN
License: UNKNOWN
Platform: UNKNOWN
Requires-Dist: paho-mqtt
Requires-Dist: python-mpd2
